dpt_vfs/__init__.py
dpt_vfs/abstract.py
dpt_vfs/abstract_watcher.py
dpt_vfs/file_like_wrapper_mixin.py
dpt_vfs/implementation.py
dpt_vfs/watcher_implementation.py
dpt_vfs/dpt_vfs/__init__.py
dpt_vfs/dpt_vfs/file/__init__.py
dpt_vfs/dpt_vfs/file/object.py
dpt_vfs/dpt_vfs/file/watcher.py
dpt_vfs/dpt_vfs/file/watcher_mtime.py
dpt_vfs/dpt_vfs/file/watcher_pyinotify.py
dpt_vfs/dpt_vfs/file/watcher_pyinotify_callback.py
dpt_vfs/dpt_vfs/file/watcher_pyinotify_sync.py
dpt_vfs-1.0.5.data/data/docs/LICENSE
dpt_vfs-1.0.5.data/data/docs/README
dpt_vfs-1.0.5.dist-info/LICENSE
dpt_vfs-1.0.5.dist-info/METADATA
dpt_vfs-1.0.5.dist-info/WHEEL
dpt_vfs-1.0.5.dist-info/top_level.txt
dpt_vfs-1.0.5.dist-info/RECORD
